{
  "content": [
    {
      "content": null,
      "created": "2022-05-23T03:55:57.143219Z",
      "format": null,
      "last_modified": "2022-05-23T03:55:57.143219Z",
      "mimetype": null,
      "name": "exercises",
      "path": "learn-py3-beginner/exercises",
      "size": null,
      "type": "directory",
      "writable": true
    },
    {
      "content": null,
      "created": "2022-05-23T03:55:57.135220Z",
      "format": null,
      "last_modified": "2022-05-23T03:55:57.135220Z",
      "mimetype": null,
      "name": "data",
      "path": "learn-py3-beginner/data",
      "size": null,
      "type": "directory",
      "writable": true
    },
    {
      "content": null,
      "created": "2022-05-23T03:55:57.155220Z",
      "format": null,
      "last_modified": "2022-05-23T03:55:57.155220Z",
      "mimetype": null,
      "name": "notebooks",
      "path": "learn-py3-beginner/notebooks",
      "size": null,
      "type": "directory",
      "writable": true
    },
    {
      "content": null,
      "created": "2022-05-23T03:55:57.135220Z",
      "format": null,
      "last_modified": "2022-05-23T03:54:41.207106Z",
      "mimetype": "text/markdown",
      "name": "README.md",
      "path": "learn-py3-beginner/README.md",
      "size": 3320,
      "type": "file",
      "writable": true
    }
  ],
  "created": "2022-05-23T03:55:57.143219Z",
  "format": "json",
  "last_modified": "2022-05-23T03:55:57.143219Z",
  "mimetype": null,
  "name": "learn-py3-beginner",
  "path": "learn-py3-beginner",
  "size": null,
  "type": "directory",
  "writable": true
}